amdataset/__init__.py
amdataset/dataset.py
amdataset/db.py
amdataset-0.2.2.dist-info/DESCRIPTION.rst
amdataset-0.2.2.dist-info/METADATA
amdataset-0.2.2.dist-info/RECORD
amdataset-0.2.2.dist-info/WHEEL
amdataset-0.2.2.dist-info/metadata.json
amdataset-0.2.2.dist-info/top_level.txt
