Metadata-Version: 2.0
Name: amdataset
Version: 0.2.2
Summary: ```
Requires-Dist: dataset
